pybitcoinrpc/__init__.py
pybitcoinrpc/sync.py
pybitcoinrpc-0.1.7.dist-info/LICENSE
pybitcoinrpc-0.1.7.dist-info/METADATA
pybitcoinrpc-0.1.7.dist-info/WHEEL
pybitcoinrpc-0.1.7.dist-info/top_level.txt
pybitcoinrpc-0.1.7.dist-info/RECORD
