Metadata-Version: 2.1
Name: pybitcoinrpc
Version: 0.1.7
Summary: Python module for Bitcoin RPC
Home-page: https://github.com/bitpole-org/python-bitcoinrpc-client
Author: psylopunk
Author-email: psylopunk@protonmail.com
License: UNKNOWN
Platform: UNKNOWN
Classifier: Programming Language :: Python :: 3
Classifier: License :: OSI Approved :: MIT License
Classifier: Operating System :: OS Independent
Requires-Python: >=3.6
